{
  "url": "http://confreaks.com/events",
  "events": [
    {
      "title": "In Memory of Jim Weirich",
      "url": "http://confreaks.com/events/imjw2014"
    },
    {
      "title": "Big Ruby 2014",
      "url": "http://confreaks.com/events/bigruby2014"
    },
    {
      "title": "DevconTLV January 2014",
      "url": "http://confreaks.com/events/devcontlvjan2014"
    },
    {
      "title": "Garden City Ruby 2014",
      "url": "http://confreaks.com/events/gardencityruby"
    },
    {
      "title": "Ruby Conference 2013",
      "url": "http://confreaks.com/events/rubyconf2013"
    },
    {
      "title": "Farmhouse Conf 5",
      "url": "http://confreaks.com/events/farmhouseconf5"
    },
    {
      "title": "Jenkins User Conference 2013 Palo Alto",
      "url": "http://confreaks.com/events/jenkins2013"
    },
    {
      "title": "Cascadia Ruby 2013",
      "url": "http://confreaks.com/events/cascadiaruby2013"
    },
    {
      "title": "Pacific Northwest Scala 2013",
      "url": "http://confreaks.com/events/pnws2013"
    },
    {
      "title": "Wicked Good Ruby 2013",
      "url": "http://confreaks.com/events/wickedgoodruby"
    },
    {
      "title": "DevconTLV October 2013",
      "url": "http://confreaks.com/events/devcontlvoct2013"
    },
    {
      "title": "Rails Israel 2013",
      "url": "http://confreaks.com/events/railsisrael2013"
    },
    {
      "title": "Fronteers 2013",
      "url": "http://confreaks.com/events/fronteers13"
    },
    {
      "title": "ArrrrCamp 2013",
      "url": "http://confreaks.com/events/arrrrcamp2013"
    },
    {
      "title": "OpenStack On Ales 2013",
      "url": "http://confreaks.com/events/osoa2013"
    },
    {
      "title": "Rocky Mountain Ruby 2013",
      "url": "http://confreaks.com/events/rockymountainruby2013"
    },
    {
      "title": "Golden Gate Ruby Conference 2013",
      "url": "http://confreaks.com/events/gogaruco2013"
    },
    {
      "title": "Nickel City Ruby Conference 2013",
      "url": "http://confreaks.com/events/nickelcityruby2013"
    },
    {
      "title": "Ignite Buffalo 2013",
      "url": "http://confreaks.com/events/ignitebflo2013"
    },
    {
      "title": "JSConf EU 2013",
      "url": "http://confreaks.com/events/jsconfeu2013"
    },
    {
      "title": "Madison Ruby 2013",
      "url": "http://confreaks.com/events/madisonruby2013"
    },
    {
      "title": "Steel City Ruby 2013",
      "url": "http://confreaks.com/events/scrc2013"
    },
    {
      "title": "Burlington Ruby 2013",
      "url": "http://confreaks.com/events/btvruby2013"
    },
    {
      "title": "Lone Star Ruby Conference 2013",
      "url": "http://confreaks.com/events/lonestarruby2013"
    },
    {
      "title": "RubyConf India 2013",
      "url": "http://confreaks.com/events/rubyconfindia2013"
    },
    {
      "title": "DevconTLV June 2013",
      "url": "http://confreaks.com/events/devcontlvjun2013"
    },
    {
      "title": "GORUCO 2013",
      "url": "http://confreaks.com/events/goruco2013"
    },
    {
      "title": "Farmhouse Conf 4",
      "url": "http://confreaks.com/events/farmhouseconf4"
    },
    {
      "title": "RailsConf 2013",
      "url": "http://confreaks.com/events/railsconf2013"
    },
    {
      "title": "openstack Summit Portland 2013",
      "url": "http://confreaks.com/events/openstacksummitportland2013"
    },
    {
      "title": "Ruby Midwest 2013",
      "url": "http://confreaks.com/events/rmw2013"
    },
    {
      "title": "Ancient City Ruby 2013",
      "url": "http://confreaks.com/events/acr2013"
    },
    {
      "title": "MountainWest RubyConf 2013",
      "url": "http://confreaks.com/events/mwrc2013"
    },
    {
      "title": "RubyConf Uruguay 2013",
      "url": "http://confreaks.com/events/rubyconfuruguay2013"
    },
    {
      "title": "RubyConf Uruguay 2013",
      "url": "http://confreaks.com/events/RubyConfUruguay2013"
    },
    {
      "title": "Ruby On Ales 2013",
      "url": "http://confreaks.com/events/roa2013"
    },
    {
      "title": "Big Ruby 2013",
      "url": "http://confreaks.com/events/bigruby2013"
    },
    {
      "title": "LA Ruby Conference 2013",
      "url": "http://confreaks.com/events/larubyconf2013"
    },
    {
      "title": "Ruby Conf Australia 2013",
      "url": "http://confreaks.com/events/rubyconfau2013"
    },
    {
      "title": "DevconTLV Feb 2013",
      "url": "http://confreaks.com/events/devcontlvfeb2013"
    },
    {
      "title": "Erlang DC 2013",
      "url": "http://confreaks.com/events/erlangdc2013"
    },
    {
      "title": "HTML 5.tx 2013",
      "url": "http://confreaks.com/events/html5tx2013"
    },
    {
      "title": "Rails Israel 2012",
      "url": "http://confreaks.com/events/%2523railsisrael2012"
    },
    {
      "title": "Farmhouse Conf 3",
      "url": "http://confreaks.com/events/fhc3"
    },
    {
      "title": "Ruby Conference 2012",
      "url": "http://confreaks.com/events/rubyconf2012"
    },
    {
      "title": "Adhearsion Conf 2012",
      "url": "http://confreaks.com/events/adhearsionconf2012"
    },
    {
      "title": "openstack summit fall 2012",
      "url": "http://confreaks.com/events/openstackfall2012"
    },
    {
      "title": "Aloha Ruby Conf 2012",
      "url": "http://confreaks.com/events/aloharuby2012"
    },
    {
      "title": "JSConf 2012",
      "url": "http://confreaks.com/events/JSConfEU2012"
    },
    {
      "title": "ArrrrCamp 2012",
      "url": "http://confreaks.com/events/arrrrcamp2012"
    },
    {
      "title": "Fronteers 2012",
      "url": "http://confreaks.com/events/fronteersconf2012"
    },
    {
      "title": "Jenkins User Conference San Francisco 2012",
      "url": "http://confreaks.com/events/jucsf2012"
    },
    {
      "title": "LXJS  2012",
      "url": "http://confreaks.com/events/lxjs2012"
    },
    {
      "title": "PuppetConf 2012",
      "url": "http://confreaks.com/events/puppetconf2012"
    },
    {
      "title": "Rocky Mountain Ruby 2012",
      "url": "http://confreaks.com/events/rockymtnruby2012"
    },
    {
      "title": "X.Org Developer Conference 2012",
      "url": "http://confreaks.com/events/XDC2012"
    },
    {
      "title": "Golden Gate Ruby Conference 2012",
      "url": "http://confreaks.com/events/gogaruco2012"
    },
    {
      "title": "Rest Fest 2012",
      "url": "http://confreaks.com/events/restfest2012"
    },
    {
      "title": "International Conference on Functional Programming 2012",
      "url": "http://confreaks.com/events/icfp2012"
    },
    {
      "title": "Barcelona Ruby Conference 2012",
      "url": "http://confreaks.com/events/baruco2012"
    },
    {
      "title": "Windy City Rails 2012",
      "url": "http://confreaks.com/events/windycityrails2012"
    },
    {
      "title": "Madison Ruby 2012",
      "url": "http://confreaks.com/events/madisonruby2012"
    },
    {
      "title": "Cascadia Ruby 2012",
      "url": "http://confreaks.com/events/cascadiaruby2012"
    },
    {
      "title": "Steel City Ruby 2012",
      "url": "http://confreaks.com/events/scrc2012"
    },
    {
      "title": "Jax Conf 2012",
      "url": "http://confreaks.com/events/jaxconf2012"
    },
    {
      "title": "jQuery Conference San Francisco 2012",
      "url": "http://confreaks.com/events/jqcon2012"
    },
    {
      "title": "GORUCO 2012",
      "url": "http://confreaks.com/events/goruco2012"
    },
    {
      "title": "Ruby Lugdunum (RuLu) 2012",
      "url": "http://confreaks.com/events/rulu2012"
    },
    {
      "title": "Erlang Factory Lite Moscow, Russia 2012",
      "url": "http://confreaks.com/events/erlangfactorymoscow2012"
    },
    {
      "title": "Copenhagen JS 2012",
      "url": "http://confreaks.com/events/cphjs2012"
    },
    {
      "title": "Windy City DB 2012",
      "url": "http://confreaks.com/events/windycitydb2012"
    },
    {
      "title": "eurUko 2012",
      "url": "http://confreaks.com/events/euroko2012"
    },
    {
      "title": "Euro Clojure 2012",
      "url": "http://confreaks.com/events/euroclojure2012"
    },
    {
      "title": "Web Rebels 2012",
      "url": "http://confreaks.com/events/webrebels2012"
    },
    {
      "title": "Web Directions Code 2012",
      "url": "http://confreaks.com/events/webdirectionscode2012"
    },
    {
      "title": "Chef Conf 2012",
      "url": "http://confreaks.com/events/chefconf2012"
    },
    {
      "title": "Farmhouse Conf 2",
      "url": "http://confreaks.com/events/farmhouseconf2"
    },
    {
      "title": "DevCon5 2012",
      "url": "http://confreaks.com/events/devcon52012"
    },
    {
      "title": "The Next Web 2012",
      "url": "http://confreaks.com/events/thenextweb2012"
    },
    {
      "title": "RailsConf 2012",
      "url": "http://confreaks.com/events/railsconf2012"
    },
    {
      "title": "Ignite RailsConf 2012",
      "url": "http://confreaks.com/events/igniterails2012"
    },
    {
      "title": "railsberry 2012",
      "url": "http://confreaks.com/events/railsberry2012"
    },
    {
      "title": "Windy City Go 2012",
      "url": "http://confreaks.com/events/windycitygo2012"
    },
    {
      "title": "Erlang Factory SF Bay Area 2012",
      "url": "http://confreaks.com/events/erlangfactorysf2012"
    },
    {
      "title": "RubyConf India 2012",
      "url": "http://confreaks.com/events/rubyconfindia2012"
    },
    {
      "title": "Ruby Nation 2012",
      "url": "http://confreaks.com/events/rubynation2012"
    },
    {
      "title": "MountainWest RubyConf 2012",
      "url": "http://confreaks.com/events/mwrc2012"
    },
    {
      "title": "Northeast Scala Symposium 2012",
      "url": "http://confreaks.com/events/nescalasymposium2012"
    },
    {
      "title": "Erlang Factory Lite Krakow, Poland 2012",
      "url": "http://confreaks.com/events/erlangfactorykrakow"
    },
    {
      "title": "Ruby On Ales 2012",
      "url": "http://confreaks.com/events/roa2012"
    },
    {
      "title": "Airbnb Tech Talks 2012",
      "url": "http://confreaks.com/events/airbnbtechtalks2012"
    },
    {
      "title": "Web Directions South 2012",
      "url": "http://confreaks.com/events/webdirectionssouth2012"
    },
    {
      "title": "AltDevConf  2012",
      "url": "http://confreaks.com/events/altdevconf2012"
    },
    {
      "title": "jQuery Conference UK 2012",
      "url": "http://confreaks.com/events/jqconfuk2012"
    },
    {
      "title": "LA Ruby Conference 2012",
      "url": "http://confreaks.com/events/larubyconf2012"
    },
    {
      "title": "meet.js SUMMIT 2012",
      "url": "http://confreaks.com/events/meetjs2012"
    },
    {
      "title": "Waza 2012",
      "url": "http://confreaks.com/events/waza2012"
    },
    {
      "title": "Ruby Midwest 2011",
      "url": "http://confreaks.com/events/rubymidwest2011"
    },
    {
      "title": "Ruby Manor 3",
      "url": "http://confreaks.com/events/rubymanor3"
    },
    {
      "title": "MagRails 2011",
      "url": "http://confreaks.com/events/magrails2011"
    },
    {
      "title": "Adhearsion Conf 2011",
      "url": "http://confreaks.com/events/adhearsionconf2011"
    },
    {
      "title": "ArrrrCamp 2011",
      "url": "http://confreaks.com/events/arrrrcamp2011"
    },
    {
      "title": "Fronteers 2011",
      "url": "http://confreaks.com/events/fronteersconf2011"
    },
    {
      "title": "JSConf 2011",
      "url": "http://confreaks.com/events/JSConfEU2011"
    },
    {
      "title": "Ruby Conference 2011",
      "url": "http://confreaks.com/events/rubyconf2011"
    },
    {
      "title": "Windy City Rails 2011",
      "url": "http://confreaks.com/events/windycityrails2011"
    },
    {
      "title": "Golden Gate Ruby Conference 2011",
      "url": "http://confreaks.com/events/gogaruco2011"
    },
    {
      "title": "Rocky Mountain Ruby 2011",
      "url": "http://confreaks.com/events/rockymtnruby2011"
    },
    {
      "title": "Madison Ruby 2011",
      "url": "http://confreaks.com/events/madisonruby2011"
    },
    {
      "title": "Lone Star Ruby Conference 2011",
      "url": "http://confreaks.com/events/lsrc2011"
    },
    {
      "title": "Cascadia Ruby 2011",
      "url": "http://confreaks.com/events/cascadiaruby2011"
    },
    {
      "title": "Windy City DB 2011",
      "url": "http://confreaks.com/events/windycitydb2011"
    },
    {
      "title": "Farmhouse Conf 2011",
      "url": "http://confreaks.com/events/farmhouseconf"
    },
    {
      "title": "Windy City Go 2011",
      "url": "http://confreaks.com/events/windycitygo2011"
    },
    {
      "title": "Scotland Ruby  2011",
      "url": "http://confreaks.com/events/scotlandruby2011"
    },
    {
      "title": "Ruby On Ales 2011",
      "url": "http://confreaks.com/events/roa2011"
    },
    {
      "title": "MountainWest RubyConf 2011",
      "url": "http://confreaks.com/events/mwrc2011"
    },
    {
      "title": "LA Ruby Conference 2011",
      "url": "http://confreaks.com/events/larubyconf2011"
    },
    {
      "title": "Ruby Conference 2010",
      "url": "http://confreaks.com/events/rubyconf2010"
    },
    {
      "title": "RubyConf Uruguay 2010",
      "url": "http://confreaks.com/events/rubyconfuruguay2010"
    },
    {
      "title": "ArrrrCamp 2010",
      "url": "http://confreaks.com/events/arrrrcamp2010"
    },
    {
      "title": "Fronteers 2010",
      "url": "http://confreaks.com/events/fronteersconf2010"
    },
    {
      "title": "Mountain rb 2010",
      "url": "http://confreaks.com/events/mountainrb2010"
    },
    {
      "title": "Sunny Conf 2010",
      "url": "http://confreaks.com/events/sunnyconf2010"
    },
    {
      "title": "Golden Gate Ruby Conference 2010",
      "url": "http://confreaks.com/events/gogaruco2010"
    },
    {
      "title": "Windy City Rails 2010",
      "url": "http://confreaks.com/events/windycityrails2010"
    },
    {
      "title": "Ruby|Web Conference 2010",
      "url": "http://confreaks.com/events/rubyweb2010"
    },
    {
      "title": "Ruby Hoedown 2010",
      "url": "http://confreaks.com/events/rubyhoedown2010"
    },
    {
      "title": "Lone Star Ruby Conference 2010",
      "url": "http://confreaks.com/events/lsrc2010"
    },
    {
      "title": "Emerging Languages Camp 2010",
      "url": "http://confreaks.com/events/elcamp2010"
    },
    {
      "title": "Windy City DB 2010",
      "url": "http://confreaks.com/events/windycitydb2010"
    },
    {
      "title": "Agile Roots 2010",
      "url": "http://confreaks.com/events/agileroots2010"
    },
    {
      "title": "MountainWest RubyConf 2010",
      "url": "http://confreaks.com/events/mwrc2010"
    },
    {
      "title": "LA Ruby Conference 2010",
      "url": "http://confreaks.com/events/larubyconf2010"
    },
    {
      "title": "Ruby Manor Harder",
      "url": "http://confreaks.com/events/rubymanor2"
    },
    {
      "title": "JRuby Conference 2009",
      "url": "http://confreaks.com/events/jrubyconf2009"
    },
    {
      "title": "Ruby Conference 2009",
      "url": "http://confreaks.com/events/rubyconf2009"
    },
    {
      "title": "Windy City Rails 2009",
      "url": "http://confreaks.com/events/windycityrails2009"
    },
    {
      "title": "Lone Star Ruby Conference 2009",
      "url": "http://confreaks.com/events/lsrc2009"
    },
    {
      "title": "Agile Roots 2009",
      "url": "http://confreaks.com/events/agileroots2009"
    },
    {
      "title": "GORUCO 2009",
      "url": "http://confreaks.com/events/goruco2009"
    },
    {
      "title": "Golden Gate Ruby Conference 2009",
      "url": "http://confreaks.com/events/gogaruco2009"
    },
    {
      "title": "LA Ruby Conference 2009",
      "url": "http://confreaks.com/events/larubyconf2009"
    },
    {
      "title": "MountainWest RubyConf 2009",
      "url": "http://confreaks.com/events/mwrc2009"
    },
    {
      "title": "Acts as Conference 2009",
      "url": "http://confreaks.com/events/aac2009"
    },
    {
      "title": "Ruby Manor",
      "url": "http://confreaks.com/events/rubymanor1"
    },
    {
      "title": "Ruby Conference 2008",
      "url": "http://confreaks.com/events/rubyconf2008"
    },
    {
      "title": "Ruby Hoedown 2008",
      "url": "http://confreaks.com/events/rubyhoedown2008"
    },
    {
      "title": "GORUCO 2008",
      "url": "http://confreaks.com/events/goruco2008"
    },
    {
      "title": "MountainWest RubyConf 2008",
      "url": "http://confreaks.com/events/mwrc2008"
    },
    {
      "title": "Ruby Conference 2007",
      "url": "http://confreaks.com/events/rubyconf2007"
    },
    {
      "title": "Ruby Hoedown 2007",
      "url": "http://confreaks.com/events/rubyhoedown2007"
    },
    {
      "title": "MountainWest RubyConf 2007",
      "url": "http://confreaks.com/events/mwrc2007"
    }
  ]
}